unidiff/__init__.py
unidiff/__version__.py
unidiff/constants.py
unidiff/errors.py
unidiff/patch.py
unidiff-0.7.2.data/scripts/unidiff
unidiff-0.7.2.dist-info/LICENSE
unidiff-0.7.2.dist-info/METADATA
unidiff-0.7.2.dist-info/WHEEL
unidiff-0.7.2.dist-info/top_level.txt
unidiff-0.7.2.dist-info/RECORD
