Metadata-Version: 2.1
Name: unidiff
Version: 0.7.2
Summary: Unified diff parsing/metadata extraction library.
Home-page: http://github.com/matiasb/python-unidiff
Author: Matias Bordese
Author-email: mbordese@gmail.com
License: MIT
Keywords: unified,diff,parse,metadata
Platform: UNKNOWN
Classifier: Intended Audience :: Developers
Classifier: Development Status :: 4 - Beta
Classifier: Programming Language :: Python :: 2
Classifier: Programming Language :: Python :: 2.7
Classifier: Programming Language :: Python :: 3
Classifier: Programming Language :: Python :: 3.6
Classifier: Programming Language :: Python :: 3.7
Classifier: Programming Language :: Python :: 3.8
License-File: LICENSE
